Metadata-Version: 2.1
Name: reduce-df
Version: 0.0.1
Summary: optimize local memory usages
Home-page: https://github.com/KeyPatAnalytics/reduce_df
Author: Keyela Patatchona
Author-email: patatchona@outlook.com
License: MIT
Keywords: data nalysis,data frame,size reduction,less memory
Classifier: Development Status :: 5 - Production/Stable
Classifier: Intended Audience :: Education
Classifier: Operating System :: Microsoft :: Windows :: Windows 10
Classifier: License :: OSI Approved :: MIT License
Classifier: Programming Language :: Python :: 3
License-File: Licence.txt
